news_dashboard/__init__.py
news_dashboard/news_api.py
news_dashboard-0.1.dist-info/METADATA
news_dashboard-0.1.dist-info/WHEEL
news_dashboard-0.1.dist-info/top_level.txt
news_dashboard-0.1.dist-info/RECORD
